cyberpoweredpc.py
cyberpoweredpc-0.0.8.dist-info/LICENSE
cyberpoweredpc-0.0.8.dist-info/WHEEL
cyberpoweredpc-0.0.8.dist-info/METADATA
cyberpoweredpc-0.0.8.dist-info/RECORD
