Metadata-Version: 2.1
Name: cyberpoweredpc
Version: 0.0.8
Summary: A cyber-powered PC builder for cyberpowerpc.com
Home-page: https://github.com/daredoes/cyberpoweredpc
License: GPL-3.0-only
Author: DareDoes
Requires-Python: >=3.9,<4.0
Classifier: License :: OSI Approved :: GNU General Public License v3 (GPLv3)
Classifier: Programming Language :: Python :: 3
Classifier: Programming Language :: Python :: 3.9
Requires-Dist: chromedriver-autoinstaller (>=0.2.2,<0.3.0)
Requires-Dist: easygui (==0.98.2)
Requires-Dist: fire (>=0.4.0,<0.5.0)
Requires-Dist: selenium (==3.141.0)
Project-URL: Repository, https://github.com/daredoes/cyberpoweredpc
